install_command/__init__.py
install_command-0.2.0.dist-info/METADATA
install_command-0.2.0.dist-info/WHEEL
install_command-0.2.0.dist-info/entry_points.txt
install_command-0.2.0.dist-info/RECORD
